setup.py
pybioseq/__init__.py
pybioseq/converter.py
pybioseq/fasta.py
pybioseq.egg-info/PKG-INFO
pybioseq.egg-info/SOURCES.txt
pybioseq.egg-info/dependency_links.txt
pybioseq.egg-info/top_level.txt
test/test.py