Metadata-Version: 2.4
Name: pybioseq
Version: 0.0.2
Summary: A Python package for biological sequence manipulation and fasta file editing.
Home-page: 
Author: Xiaoyang Liu
Author-email: liuxiaoyang_Q@outlook.com
License: MIT
Dynamic: author
Dynamic: author-email
Dynamic: license
Dynamic: summary
